{
  "type": "Feature",
  "properties": {
    "leitstellen_id": "DE-RP-ILS-WESTER",
    "leitstellenname": "ILS Westerwaldkreis",
    "bundesland": "RP",
    "traeger": null,
    "betreiber": null,
    "adresse": null,
    "telefon": null,
    "notruf": null,
    "quelltyp": "recht_abgeleitet",
    "funkgruppen": [],
    "frequenzschema": null,
    "geometry_basis": "verwaltungsgrenze_abgeleitet",
    "source_url": null,
    "source_crs": null,
    "valid_from": "2026-05-12",
    "valid_to": null,
    "review_status": "needs_review",
    "bemerkung": "1:1-Kreis-Mapping aus VG250: Landkreis Westerwaldkreis"
  },
  "geometry": {
    "type": "MultiPolygon",
    "coordinates": [
      [
        [
          [
            7.680343459486209,
            50.56347790185619
          ],
          [
            7.678617504367463,
            50.563030521309
          ],
          [
            7.676772728968468,
            50.56314747313388
          ],
          [
            7.676750919697633,
            50.56186833923364
          ],
          [
            7.669713519825497,
            50.56089454426694
          ],
          [
            7.666993338478693,
            50.56356508258519
          ],
          [
            7.66639929057013,
            50.56884733479683
          ],
          [
            7.669609208129134,
            50.56869867976157
          ],
          [
            7.672268690294489,
            50.56773739574098
          ],
          [
            7.680442624053763,
            50.565821419765925
          ],
          [
            7.680343459486209,
            50.56347790185619
          ]
        ]
      ],
      [
        [
          [
            7.746978961054357,
            50.739951751643304
          ],
          [
            7.752517676747413,
            50.738183456114186
          ],
          [
            7.754625690350866,
            50.73828746709056
          ],
          [
            7.757197087529343,
            50.736061416027525
          ],
          [
            7.7584440116748485,
            50.735847836715074
          ],
          [
            7.768366307353314,
            50.73261583595601
          ],
          [
            7.769264557960834,
            50.73302418338385
          ],
          [
            7.768505763760799,
            50.73580646652583
          ],
          [
            7.772380005714987,
            50.736275935520396
          ],
          [
            7.773841368529383,
            50.73748983684796
          ],
          [
            7.778119879076301,
            50.735897763265385
          ],
          [
            7.780743084302771,
            50.734707865955826
          ],
          [
            7.782215439837528,
            50.733788032803695
          ],
          [
            7.784326852251933,
            50.73285615886949
          ],
          [
            7.786263376997203,
            50.73151498334538
          ],
          [
            7.78693180633274,
            50.73124252686703
          ],
          [
            7.789411065782446,
            50.73130058549889
          ],
          [
            7.79117876723229,
            50.73115287114901
          ],
          [
            7.793961464310732,
            50.730137489014986
          ],
          [
            7.79624712270107,
            50.73035294421027
          ],
          [
            7.797741742219287,
            50.729775582800855
          ],
          [
            7.7984998736790825,
            50.72966722073169
          ],
          [
            7.799542490374928,
            50.72979057965115
          ],
          [
            7.800524920378936,
            50.73021864995032
          ],
          [
            7.804752438884085,
            50.731199477660866
          ],
          [
            7.80723755008922,
            50.72968165798565
          ],
          [
            7.808217815190238,
            50.729902528080125
          ],
          [
            7.808500557976054,
            50.728198414349244
          ],
          [
            7.807853571921276,
            50.72564435543651
          ],
          [
            7.804702699609088,
            50.722239711018844
          ],
          [
            7.80148131719016,
            50.71957162512147
          ],
          [
            7.800431157681398,
            50.71639586558781
          ],
          [
            7.802495029651455,
            50.716020803935336
          ],
          [
            7.802429561248568,
            50.71420954665014
          ],
          [
            7.8039217583092055,
            50.7131728772453
          ],
          [
            7.805244797650487,
            50.71088975152691
          ],
          [
            7.8070958835667,
            50.70952826575299
          ],
          [
            7.808236319197477,
            50.70991493700811
          ],
          [
            7.814539963737366,
            50.70731526168248
          ],
          [
            7.8182561369526375,
            50.70852687003
          ],
          [
            7.8184584009436,
            50.70772123476477
          ],
          [
            7.814411763044502,
            50.706339899530334
          ],
          [
            7.813854311674428,
            50.705678704856716
          ],
          [
            7.814839292157156,
            50.70383781795898
          ],
          [
            7.815989675496796,
            50.70429667410317
          ],
          [
            7.81655549844888,
            50.70555228856033
          ],
          [
            7.820147604406921,
            50.707688328798525
          ],
          [
            7.823187144696144,
            50.70809179481621
          ],
          [
            7.826606995756048,
            50.709530367289425
          ],
          [
            7.829245057575194,
            50.710014432163376
          ],
          [
            7.836416804452966,
            50.71180931666712
          ],
          [
            7.84219622699705,
            50.708430807501585
          ],
          [
            7.848110864157738,
            50.70590145027984
          ],
          [
            7.85509224922906,
            50.7012983944014
          ],
          [
            7.859955205656796,
            50.69678168839971
          ],
          [
            7.859097132545609,
            50.695411600019746
          ],
          [
            7.855114734466131,
            50.69364600954038
          ],
          [
            7.8530929413342685,
            50.69355476143587
          ],
          [
            7.853096237413371,
            50.69299662479039
          ],
          [
            7.854546690012707,
            50.68966251845089
          ],
          [
            7.854766482335532,
            50.68528288113895
          ],
          [
            7.8579411282778135,
            50.68352773450902
          ],
          [
            7.863506141678953,
            50.68260129961851
          ],
          [
            7.869349998068002,
            50.681248782617935
          ],
          [
            7.883613940080081,
            50.67907835947758
          ],
          [
            7.887764518669405,
            50.6791001370476
          ],
          [
            7.889174044606797,
            50.6787268117498
          ],
          [
            7.889972541566981,
            50.67924519827005
          ],
          [
            7.890239030730592,
            50.68046146317677
          ],
          [
            7.892900687249992,
            50.68177293134528
          ],
          [
            7.890423168276631,
            50.684012901125634
          ],
          [
            7.886562075450322,
            50.68514118464801
          ],
          [
            7.885953131085246,
            50.68589270576735
          ],
          [
            7.880186955161481,
            50.68661759108015
          ],
          [
            7.874500461711712,
            50.688190314182165
          ],
          [
            7.875228927425379,
            50.688846078624074
          ],
          [
            7.8754124417354054,
            50.68961552411581
          ],
          [
            7.87513995597491,
            50.69042864520913
          ],
          [
            7.875487274859526,
            50.69105775317601
          ],
          [
            7.876284045004017,
            50.69150798256235
          ],
          [
            7.878019648948883,
            50.69164636165459
          ],
          [
            7.878699652287383,
            50.69190485814072
          ],
          [
            7.879186594027125,
            50.692825222382595
          ],
          [
            7.879118951279792,
            50.69403013325262
          ],
          [
            7.8821997266617725,
            50.69545936811949
          ],
          [
            7.881736220331461,
            50.69639422740911
          ],
          [
            7.88211834299851,
            50.69893279769282
          ],
          [
            7.883609372222412,
            50.70367371718101
          ],
          [
            7.88574348723885,
            50.70862124090027
          ],
          [
            7.889053144277633,
            50.713836804028475
          ],
          [
            7.890930334159446,
            50.71576980979337
          ],
          [
            7.902630847914149,
            50.718805897928554
          ],
          [
            7.907999097286791,
            50.71892620713709
          ],
          [
            7.916266530251997,
            50.71676118354882
          ],
          [
            7.923044090054807,
            50.71318495576862
          ],
          [
            7.931085456087313,
            50.710455688553054
          ],
          [
            7.939912426913418,
            50.71031813129234
          ],
          [
            7.946515369894149,
            50.709104520072245
          ],
          [
            7.947015149998908,
            50.70883934606724
          ],
          [
            7.956539314947234,
            50.701275991683474
          ],
          [
            7.96633123877276,
            50.69536934218499
          ],
          [
            7.968224844740646,
            50.693907298698704
          ],
          [
            7.968814438382479,
            50.69218263325019
          ],
          [
            7.967130176741357,
            50.68874267096231
          ],
          [
            7.967645212486,
            50.685466289782816
          ],
          [
            7.966129076866165,
            50.68300342314904
          ],
          [
            7.963922604618934,
            50.678129962530875
          ],
          [
            7.966248453133289,
            50.67756873092038
          ],
          [
            7.974438381300915,
            50.67625335045055
          ],
          [
            7.976419293819496,
            50.675748802180536
          ],
          [
            7.979226237323685,
            50.67583382721131
          ],
          [
            7.980852975701171,
            50.67555960441736
          ],
          [
            7.98453263907514,
            50.67544912251349
          ],
          [
            7.9865798497839995,
            50.675743559768065
          ],
          [
            7.9928857414148204,
            50.67598844127417
          ],
          [
            7.993790652019832,
            50.67628713832885
          ],
          [
            7.994972925357544,
            50.676998611769505
          ],
          [
            7.99602496003987,
            50.67821711295823
          ],
          [
            7.995886401751811,
            50.6790348395203
          ],
          [
            7.996082691143025,
            50.67950861460135
          ],
          [
            7.9991642033762345,
            50.68084299043942
          ],
          [
            8.00036314413071,
            50.68099410968007
          ],
          [
            8.001308862586365,
            50.68173447769148
          ],
          [
            8.002805131107024,
            50.68231456408013
          ],
          [
            8.003457584719552,
            50.68439455276209
          ],
          [
            8.00408436377209,
            50.68511236240557
          ],
          [
            8.004525543889965,
            50.68607657733266
          ],
          [
            8.005207629905579,
            50.68827354950495
          ],
          [
            8.014903141849361,
            50.690633848508625
          ],
          [
            8.0179199281381,
            50.69177984564732
          ],
          [
            8.028441040163653,
            50.69700061182035
          ],
          [
            8.032458988190719,
            50.69768052833361
          ],
          [
            8.035972402475222,
            50.697179218581645
          ],
          [
            8.03968994233647,
            50.69737534582403
          ],
          [
            8.041386284420584,
            50.696655176817934
          ],
          [
            8.059656032671823,
            50.69504331116376
          ],
          [
            8.064205846986226,
            50.69938835968274
          ],
          [
            8.065758226250432,
            50.699811377983046
          ],
          [
            8.071287040676708,
            50.700232418043115
          ],
          [
            8.071321641487845,
            50.70102331570962
          ],
          [
            8.071103872554312,
            50.70166692552484
          ],
          [
            8.07506377216301,
            50.70484681305053
          ],
          [
            8.079578597104604,
            50.70608462424467
          ],
          [
            8.082479451921522,
            50.70290436467741
          ],
          [
            8.088723334928885,
            50.70360176488738
          ],
          [
            8.09917332057285,
            50.70355792491379
          ],
          [
            8.109820137069436,
            50.69800777408301
          ],
          [
            8.120690765149368,
            50.68829323265519
          ],
          [
            8.121063881411004,
            50.68542016861427
          ],
          [
            8.125776742857902,
            50.685814049501865
          ],
          [
            8.125813889449084,
            50.68341120267681
          ],
          [
            8.1255171337208,
            50.68283796878669
          ],
          [
            8.124733640820534,
            50.68236276934012
          ],
          [
            8.123984937215308,
            50.68120410478518
          ],
          [
            8.119700185940898,
            50.67714600917909
          ],
          [
            8.118817777742072,
            50.676668731051144
          ],
          [
            8.116422427102442,
            50.67613327404333
          ],
          [
            8.11258357828164,
            50.675567983219196
          ],
          [
            8.110229725140035,
            50.67090117552159
          ],
          [
            8.109687953560975,
            50.665155485036244
          ],
          [
            8.110092340766814,
            50.6572507793765
          ],
          [
            8.113960563434185,
            50.652496412431816
          ],
          [
            8.118295890469538,
            50.65078533656431
          ],
          [
            8.123785691870658,
            50.64529887095943
          ],
          [
            8.127491728251726,
            50.645086916978805
          ],
          [
            8.12650051174435,
            50.64146565630069
          ],
          [
            8.128755749369056,
            50.6385029784477
          ],
          [
            8.130984285771538,
            50.63623729713349
          ],
          [
            8.131984666970864,
            50.63688795587358
          ],
          [
            8.140272237632841,
            50.631710129107425
          ],
          [
            8.14088486528135,
            50.63022826662635
          ],
          [
            8.13917892902964,
            50.62953626626235
          ],
          [
            8.141400684990032,
            50.62673692956684
          ],
          [
            8.139649213492019,
            50.62582795067337
          ],
          [
            8.14037442717676,
            50.62435739401871
          ],
          [
            8.137804944152903,
            50.62339566831089
          ],
          [
            8.138681637336843,
            50.620046751210324
          ],
          [
            8.137446733447687,
            50.61950231029624
          ],
          [
            8.13555885387661,
            50.619520856163554
          ],
          [
            8.13534443396064,
            50.618430343836
          ],
          [
            8.137736045391312,
            50.61822202900106
          ],
          [
            8.131491718511656,
            50.61289221699321
          ],
          [
            8.126018672369536,
            50.61009313693826
          ],
          [
            8.127958305512786,
            50.60771903166137
          ],
          [
            8.133716714872222,
            50.60602768694961
          ],
          [
            8.143406524236825,
            50.603507120075825
          ],
          [
            8.147507999377975,
            50.602114371029955
          ],
          [
            8.14925851399099,
            50.599368335328975
          ],
          [
            8.151592166706681,
            50.59937080162835
          ],
          [
            8.15216089899265,
            50.593674981131436
          ],
          [
            8.150030081558668,
            50.58907652895417
          ],
          [
            8.147574004449067,
            50.5858937497731
          ],
          [
            8.146953082738651,
            50.583900612167106
          ],
          [
            8.147141933025443,
            50.58211302294025
          ],
          [
            8.14296124151077,
            50.57605581785536
          ],
          [
            8.141744098208358,
            50.57348714978983
          ],
          [
            8.140185777486478,
            50.572014578188266
          ],
          [
            8.139596324064941,
            50.56800553514749
          ],
          [
            8.139671591639903,
            50.56651270447967
          ],
          [
            8.137911970133837,
            50.565810537584845
          ],
          [
            8.136133784505917,
            50.56547705449366
          ],
          [
            8.136410998473457,
            50.56446547910681
          ],
          [
            8.134670199313033,
            50.563952692971256
          ],
          [
            8.135128177817359,
            50.56244069943292
          ],
          [
            8.133350568059564,
            50.56181911016058
          ],
          [
            8.132188961774819,
            50.55796031925576
          ],
          [
            8.131939348619808,
            50.557027964155175
          ],
          [
            8.13419385140546,
            50.55631802306989
          ],
          [
            8.137912756191444,
            50.550947864273915
          ],
          [
            8.135824979181258,
            50.55004088464863
          ],
          [
            8.126222548333544,
            50.54853837429289
          ],
          [
            8.121812952810147,
            50.54884365629193
          ],
          [
            8.118991994590441,
            50.54847038762658
          ],
          [
            8.118807500372021,
            50.54681915721914
          ],
          [
            8.116468673782695,
            50.5453034783779
          ],
          [
            8.113235027684258,
            50.54499355431698
          ],
          [
            8.111169550757763,
            50.54366346497997
          ],
          [
            8.110809232864664,
            50.54186453698442
          ],
          [
            8.112118589161339,
            50.540289235234745
          ],
          [
            8.114081832184407,
            50.53918656743193
          ],
          [
            8.116076255518742,
            50.53857964008912
          ],
          [
            8.117859222861197,
            50.53879652469994
          ],
          [
            8.118995653840967,
            50.53978323705884
          ],
          [
            8.120880706630928,
            50.539660093728706
          ],
          [
            8.117738250745093,
            50.53450892645538
          ],
          [
            8.115028738882,
            50.53584828550266
          ],
          [
            8.107961506030843,
            50.53427955187292
          ],
          [
            8.105355337691224,
            50.53414444571878
          ],
          [
            8.103427207021772,
            50.532628005734956
          ],
          [
            8.101133021273888,
            50.53384964140828
          ],
          [
            8.100831152096639,
            50.534779609113365
          ],
          [
            8.098818972106654,
            50.534629703546806
          ],
          [
            8.098369860259865,
            50.53512448560488
          ],
          [
            8.094556290426004,
            50.53535588248592
          ],
          [
            8.092605755009007,
            50.536658570681126
          ],
          [
            8.090714655295372,
            50.535387931254384
          ],
          [
            8.087303551266048,
            50.53853949165623
          ],
          [
            8.080032265460364,
            50.53846817839162
          ],
          [
            8.07693020786697,
            50.539177262569915
          ],
          [
            8.072570701901322,
            50.53879751399704
          ],
          [
            8.070521466881337,
            50.53799815673462
          ],
          [
            8.069049688147734,
            50.545943365785284
          ],
          [
            8.067985243964037,
            50.54630803704044
          ],
          [
            8.067012199886545,
            50.54708874232021
          ],
          [
            8.066421972908152,
            50.548930811174486
          ],
          [
            8.058042833132573,
            50.55029318319813
          ],
          [
            8.05721588765896,
            50.551247952129195
          ],
          [
            8.05612715372258,
            50.55099082753427
          ],
          [
            8.055124176877692,
            50.55179781250474
          ],
          [
            8.054284338917546,
            50.551644973145876
          ],
          [
            8.053810636514898,
            50.55259820506253
          ],
          [
            8.049348905884191,
            50.55280060224005
          ],
          [
            8.047743044972936,
            50.55378377334101
          ],
          [
            8.047765103574262,
            50.55498158739173
          ],
          [
            8.04610399655936,
            50.557016868322016
          ],
          [
            8.041611266502645,
            50.5569932512362
          ],
          [
            8.042908555619764,
            50.55381595384679
          ],
          [
            8.040995700739543,
            50.552568848500364
          ],
          [
            8.037519008096787,
            50.5515044033234
          ],
          [
            8.035454031187172,
            50.5515413321866
          ],
          [
            8.033965286394396,
            50.55190563569218
          ],
          [
            8.033238150846522,
            50.55122389415095
          ],
          [
            8.028374600523367,
            50.550558727041974
          ],
          [
            8.028555368035917,
            50.54996710891374
          ],
          [
            8.02923832938519,
            50.54963485441363
          ],
          [
            8.029038634426527,
            50.5485591603704
          ],
          [
            8.028002511693476,
            50.54694104724957
          ],
          [
            8.028459114786015,
            50.545415499889096
          ],
          [
            8.028294119030814,
            50.54450110914787
          ],
          [
            8.023841058949074,
            50.54214592736594
          ],
          [
            8.024941102741458,
            50.54164738167586
          ],
          [
            8.018461687897227,
            50.536484647820814
          ],
          [
            8.017209822575216,
            50.53691684327585
          ],
          [
            8.014544942020718,
            50.53495986817564
          ],
          [
            8.012151651578808,
            50.5324145055518
          ],
          [
            8.012807281830527,
            50.531771448339626
          ],
          [
            8.011075710328976,
            50.53059974298591
          ],
          [
            8.010308141332649,
            50.53069120634078
          ],
          [
            8.009058246861667,
            50.52949385637711
          ],
          [
            8.004646508172417,
            50.53064985520811
          ],
          [
            8.003419506255147,
            50.52956012881269
          ],
          [
            8.002791216975872,
            50.52835899868022
          ],
          [
            7.999234466284332,
            50.52725559819471
          ],
          [
            7.996302350226905,
            50.52450913393638
          ],
          [
            7.992857647786021,
            50.52211155495883
          ],
          [
            7.995681371792095,
            50.51948108628074
          ],
          [
            7.996564082012242,
            50.51723155225025
          ],
          [
            7.994553785965392,
            50.51600851164308
          ],
          [
            7.9907558638862,
            50.51468351581801
          ],
          [
            7.989571842861788,
            50.51306423620909
          ],
          [
            7.9854747765660425,
            50.51179556271857
          ],
          [
            7.984002353376047,
            50.5118714670551
          ],
          [
            7.982937247884816,
            50.511461090890904
          ],
          [
            7.98465889042203,
            50.50963508405804
          ],
          [
            7.984533753771423,
            50.50802084363687
          ],
          [
            7.98588204054002,
            50.50341379898741
          ],
          [
            7.986893011942177,
            50.50167129331165
          ],
          [
            7.988513877211769,
            50.49960896942845
          ],
          [
            7.989966931763392,
            50.49856929236658
          ],
          [
            7.98669591080151,
            50.496922501145775
          ],
          [
            7.982969374583563,
            50.49587785649821
          ],
          [
            7.98049258024751,
            50.49574270141602
          ],
          [
            7.978902889368633,
            50.49538382801752
          ],
          [
            7.98123517582329,
            50.49374229643948
          ],
          [
            7.980382107932056,
            50.49228318787707
          ],
          [
            7.980978951363891,
            50.49063070974019
          ],
          [
            7.978732071560915,
            50.487799677845224
          ],
          [
            7.978981946984233,
            50.486301667862186
          ],
          [
            7.980079627075143,
            50.48556944301656
          ],
          [
            7.9791982249999,
            50.48464087111118
          ],
          [
            7.982057129906309,
            50.48264174125402
          ],
          [
            7.9856159143454155,
            50.48258443126313
          ],
          [
            7.986255231106291,
            50.479870526318614
          ],
          [
            7.987484181421289,
            50.479843321846914
          ],
          [
            7.987385406092561,
            50.47852675490566
          ],
          [
            7.98580773207259,
            50.47663774631957
          ],
          [
            7.986513541668071,
            50.47505064742314
          ],
          [
            7.988974819027822,
            50.4754554426805
          ],
          [
            7.987368282637423,
            50.47410599495246
          ],
          [
            7.987667910145119,
            50.4727260966714
          ],
          [
            7.9917003938308575,
            50.47223781013093
          ],
          [
            7.994821077392029,
            50.47059520276217
          ],
          [
            7.995113260858194,
            50.469350170488795
          ],
          [
            7.9946029890350525,
            50.468339760873235
          ],
          [
            7.998007393503368,
            50.46601579486031
          ],
          [
            7.9987374425882365,
            50.46566578257711
          ],
          [
            7.999133702127489,
            50.463789281874796
          ],
          [
            7.999617132432553,
            50.463120913841976
          ],
          [
            8.000653943041012,
            50.46257174651102
          ],
          [
            8.002132304979847,
            50.46213933933308
          ],
          [
            8.010474863443907,
            50.46057251288172
          ],
          [
            8.009522626519104,
            50.45831924476492
          ],
          [
            8.010766000952326,
            50.45269242610988
          ],
          [
            8.008545164459864,
            50.4517621180362
          ],
          [
            8.00751559593805,
            50.45070451763285
          ],
          [
            8.008110241354364,
            50.44879981034586
          ],
          [
            8.000115370208167,
            50.4474831157224
          ],
          [
            8.001020848788476,
            50.44530610465986
          ],
          [
            7.990632849481834,
            50.44393675235554
          ],
          [
            7.9893916707554995,
            50.442892369751746
          ],
          [
            7.988854441326386,
            50.440548924219314
          ],
          [
            7.989391520269237,
            50.439732383579575
          ],
          [
            7.97783250935832,
            50.43814723136325
          ],
          [
            7.975182452194472,
            50.43762097528737
          ],
          [
            7.975119954618,
            50.43590005829612
          ],
          [
            7.978219894106705,
            50.43434751708981
          ],
          [
            7.9796762109366055,
            50.4355767986331
          ],
          [
            7.982824288800498,
            50.43601481577977
          ],
          [
            7.985808429340707,
            50.43556688854317
          ],
          [
            7.98809505829037,
            50.435508788519115
          ],
          [
            7.9890331298034205,
            50.43378271735183
          ],
          [
            7.9851642414536,
            50.43338313472583
          ],
          [
            7.984375898125918,
            50.43231257412874
          ],
          [
            7.984583382702597,
            50.431596884524254
          ],
          [
            7.986101071811792,
            50.430891820326536
          ],
          [
            7.987514992033073,
            50.42949125562241
          ],
          [
            7.987782203405303,
            50.42792159977174
          ],
          [
            7.985671419037958,
            50.42628199729838
          ],
          [
            7.983861707710277,
            50.4258643177476
          ],
          [
            7.983788509794158,
            50.42486340443338
          ],
          [
            7.98296522707992,
            50.42258210328939
          ],
          [
            7.981587832143605,
            50.42070096475092
          ],
          [
            7.982168480729573,
            50.419858406240756
          ],
          [
            7.981239427597759,
            50.41800149319636
          ],
          [
            7.974933058427069,
            50.414217088154835
          ],
          [
            7.971335349052694,
            50.41483127636505
          ],
          [
            7.9661720231298485,
            50.41521281500075
          ],
          [
            7.964191681575583,
            50.412225230338
          ],
          [
            7.964397959420201,
            50.41023113623079
          ],
          [
            7.969375400113424,
            50.40989061367788
          ],
          [
            7.970292663831278,
            50.40698486110906
          ],
          [
            7.971559408183728,
            50.4062204653047
          ],
          [
            7.9693561631346075,
            50.4060639719158
          ],
          [
            7.967373251169204,
            50.407046650455676
          ],
          [
            7.96676374016021,
            50.40491927128973
          ],
          [
            7.966963625913405,
            50.40314838721282
          ],
          [
            7.965657097960146,
            50.401256005894346
          ],
          [
            7.963971272503434,
            50.40065165871423
          ],
          [
            7.962953669374223,
            50.40093530183671
          ],
          [
            7.959560053938333,
            50.400176169540956
          ],
          [
            7.95495993723145,
            50.39876902760863
          ],
          [
            7.953849562653716,
            50.39664676470114
          ],
          [
            7.9493626675687095,
            50.39757365771816
          ],
          [
            7.946681892201101,
            50.39690718119375
          ],
          [
            7.944788627285176,
            50.398804544087426
          ],
          [
            7.945997232942647,
            50.40066799852873
          ],
          [
            7.945518722607632,
            50.402214882719186
          ],
          [
            7.943625890614943,
            50.404900722113965
          ],
          [
            7.941023539368804,
            50.40560810008747
          ],
          [
            7.9411055410883264,
            50.40746453978172
          ],
          [
            7.93970439815685,
            50.409909180052935
          ],
          [
            7.93876209367229,
            50.41246305787004
          ],
          [
            7.937439206820341,
            50.41460137021273
          ],
          [
            7.934320747765711,
            50.41478464605501
          ],
          [
            7.9269272207349175,
            50.413747442594314
          ],
          [
            7.925293307096658,
            50.41295784905105
          ],
          [
            7.914856473690327,
            50.410856887649686
          ],
          [
            7.91293908643918,
            50.410624711149104
          ],
          [
            7.911027087241838,
            50.40952832433327
          ],
          [
            7.909731870618665,
            50.40721236886777
          ],
          [
            7.904884411352115,
            50.40672495845607
          ],
          [
            7.9046993929356875,
            50.40497417387866
          ],
          [
            7.904280809063833,
            50.40413643769443
          ],
          [
            7.901119977450174,
            50.40270557371425
          ],
          [
            7.898542619417983,
            50.401170778658035
          ],
          [
            7.895767589868821,
            50.3976147340893
          ],
          [
            7.895028464484869,
            50.39621150214674
          ],
          [
            7.894231430679937,
            50.39559923214427
          ],
          [
            7.893455462412601,
            50.39613083817799
          ],
          [
            7.895429849787034,
            50.399641802501954
          ],
          [
            7.896840836496582,
            50.40112326410572
          ],
          [
            7.894501907725089,
            50.40215067495506
          ],
          [
            7.891759740675487,
            50.40130523406939
          ],
          [
            7.890653163605473,
            50.40220745947283
          ],
          [
            7.8891923662161325,
            50.401625107936454
          ],
          [
            7.8881068454577425,
            50.40074362358523
          ],
          [
            7.88698337964287,
            50.40100109097464
          ],
          [
            7.884166556943384,
            50.402330186912025
          ],
          [
            7.879983520844994,
            50.39972127364406
          ],
          [
            7.879216089333934,
            50.399078749128364
          ],
          [
            7.880389853570351,
            50.39829291662315
          ],
          [
            7.881570465182693,
            50.39788641836509
          ],
          [
            7.882303547975973,
            50.39632765178734
          ],
          [
            7.8831883906059215,
            50.391314988341506
          ],
          [
            7.884118967553308,
            50.39003069818953
          ],
          [
            7.884638564960903,
            50.38853898207355
          ],
          [
            7.885490889277663,
            50.38815322436799
          ],
          [
            7.8861854310562025,
            50.3875658026894
          ],
          [
            7.886208938699288,
            50.387143186248665
          ],
          [
            7.88587478433884,
            50.386568385814854
          ],
          [
            7.885828244355624,
            50.38512681358873
          ],
          [
            7.8860394626791175,
            50.38411425395689
          ],
          [
            7.8859359015185335,
            50.3836977512964
          ],
          [
            7.882039530226353,
            50.3843833562569
          ],
          [
            7.878885340124757,
            50.38438350421025
          ],
          [
            7.876242981830401,
            50.385556668914646
          ],
          [
            7.874017408221452,
            50.38582096450429
          ],
          [
            7.871628613726684,
            50.385478266459344
          ],
          [
            7.868684936870437,
            50.384483584632065
          ],
          [
            7.865903796961892,
            50.385113143010365
          ],
          [
            7.865945091865049,
            50.38713983152569
          ],
          [
            7.862797650161159,
            50.38751783626842
          ],
          [
            7.859005794351923,
            50.39059095635976
          ],
          [
            7.855629169025364,
            50.39178281126093
          ],
          [
            7.854834459243191,
            50.390639110769314
          ],
          [
            7.854590696047961,
            50.38891335680634
          ],
          [
            7.852318620016791,
            50.38787270650288
          ],
          [
            7.85087374935795,
            50.38745075547369
          ],
          [
            7.8507690001590404,
            50.38506244961342
          ],
          [
            7.853445546492793,
            50.38404370045461
          ],
          [
            7.852470496440913,
            50.38335499887538
          ],
          [
            7.8535488463151,
            50.382209394995535
          ],
          [
            7.857076679299302,
            50.38057092669852
          ],
          [
            7.860897512192991,
            50.38073074410101
          ],
          [
            7.86345794704305,
            50.38026731184718
          ],
          [
            7.865337888505011,
            50.377123251657004
          ],
          [
            7.867218584553711,
            50.37697727893333
          ],
          [
            7.871247961914903,
            50.37843800612984
          ],
          [
            7.872618948968572,
            50.37859539974362
          ],
          [
            7.873483737064694,
            50.378489119165785
          ],
          [
            7.876119743238289,
            50.37742391991623
          ],
          [
            7.878571929300803,
            50.377632930329355
          ],
          [
            7.880688077717951,
            50.377050949470686
          ],
          [
            7.880281168137692,
            50.37576321675126
          ],
          [
            7.880486951522747,
            50.37484957785297
          ],
          [
            7.880022850406168,
            50.373830637161255
          ],
          [
            7.879930313665488,
            50.37246003668403
          ],
          [
            7.878610165773346,
            50.371898740893236
          ],
          [
            7.878172230217874,
            50.3706643105583
          ],
          [
            7.877534999351491,
            50.36972243707799
          ],
          [
            7.876455947677215,
            50.368626421537435
          ],
          [
            7.875589824900495,
            50.36724715418929
          ],
          [
            7.8757650255329175,
            50.36562156840745
          ],
          [
            7.876289649425995,
            50.364544156556626
          ],
          [
            7.877166678259265,
            50.3634567813259
          ],
          [
            7.877699969732552,
            50.362455639667964
          ],
          [
            7.877587297657301,
            50.36180513430973
          ],
          [
            7.876011919534072,
            50.359685068620735
          ],
          [
            7.875267612780454,
            50.35906514354002
          ],
          [
            7.8742475754054855,
            50.358660697721774
          ],
          [
            7.873152105149002,
            50.35854037092089
          ],
          [
            7.869818881918582,
            50.35901676269521
          ],
          [
            7.868779720990426,
            50.35895485488704
          ],
          [
            7.867933986357307,
            50.35863057062191
          ],
          [
            7.86746018949959,
            50.35804800632017
          ],
          [
            7.867285236613089,
            50.35585244560436
          ],
          [
            7.868018591718082,
            50.35419223735363
          ],
          [
            7.869002512130636,
            50.35337627031023
          ],
          [
            7.870679070957825,
            50.35269049269651
          ],
          [
            7.870691940874841,
            50.35139491630838
          ],
          [
            7.870250112033295,
            50.35024138610444
          ],
          [
            7.867794378581882,
            50.34909831905328
          ],
          [
            7.865158631299325,
            50.34842566643192
          ],
          [
            7.864847067780388,
            50.347959351926704
          ],
          [
            7.864988706502996,
            50.34744041119393
          ],
          [
            7.860216961174219,
            50.34747489721846
          ],
          [
            7.857424759253172,
            50.34833803295066
          ],
          [
            7.855619422734305,
            50.35036287357157
          ],
          [
            7.8543309657136975,
            50.349971120746986
          ],
          [
            7.854962582287067,
            50.35356839640147
          ],
          [
            7.853029615011555,
            50.35417903242306
          ],
          [
            7.848235290328045,
            50.352105731546786
          ],
          [
            7.843041807419312,
            50.35087830984463
          ],
          [
            7.835933334972769,
            50.35092074666845
          ],
          [
            7.835188394909622,
            50.3516507505818
          ],
          [
            7.831663086392789,
            50.351532901309284
          ],
          [
            7.826821646905382,
            50.35253676433891
          ],
          [
            7.825079999315151,
            50.35346859496688
          ],
          [
            7.823945672946423,
            50.354360529219335
          ],
          [
            7.826283423068489,
            50.35705297528822
          ],
          [
            7.823272932955217,
            50.35950384320025
          ],
          [
            7.816882844386817,
            50.359264751925934
          ],
          [
            7.815241577404006,
            50.358677196038194
          ],
          [
            7.812314863882531,
            50.35915797990668
          ],
          [
            7.809223380516209,
            50.35931970811771
          ],
          [
            7.813916875771536,
            50.362895889957656
          ],
          [
            7.812575348953591,
            50.362972561970366
          ],
          [
            7.81003304627093,
            50.36189567084387
          ],
          [
            7.805063761028566,
            50.36141907784853
          ],
          [
            7.80056984221137,
            50.361979844921066
          ],
          [
            7.799466867766279,
            50.36231406854249
          ],
          [
            7.795391291482781,
            50.36269539321107
          ],
          [
            7.792886464970318,
            50.3619521289724
          ],
          [
            7.792369127408976,
            50.360670429377684
          ],
          [
            7.791825596048086,
            50.36062174652403
          ],
          [
            7.790238112573247,
            50.36106869885869
          ],
          [
            7.788717225747394,
            50.362001585007334
          ],
          [
            7.786865895048467,
            50.36213424629337
          ],
          [
            7.7858392474042635,
            50.36187590363688
          ],
          [
            7.78453246484591,
            50.36110672682412
          ],
          [
            7.78090021739754,
            50.35844577411012
          ],
          [
            7.778105384698033,
            50.35785737900601
          ],
          [
            7.7774500246019205,
            50.35750871395709
          ],
          [
            7.777130427232433,
            50.35670881603316
          ],
          [
            7.777093492965925,
            50.35540240766789
          ],
          [
            7.77577607159794,
            50.35530814792714
          ],
          [
            7.77513788650047,
            50.35587825157101
          ],
          [
            7.7759826017766,
            50.35805916815299
          ],
          [
            7.773406826522473,
            50.35927658953113
          ],
          [
            7.773398794111534,
            50.361599352306314
          ],
          [
            7.774754889488803,
            50.36200067809148
          ],
          [
            7.773502799373495,
            50.364320573121596
          ],
          [
            7.772117063686332,
            50.366223842188894
          ],
          [
            7.767915405637572,
            50.36682630587808
          ],
          [
            7.769670619927346,
            50.37124677631665
          ],
          [
            7.774613577683154,
            50.37272198417372
          ],
          [
            7.78028012413563,
            50.376951643342245
          ],
          [
            7.789381544566078,
            50.3841714881795
          ],
          [
            7.7904324810152366,
            50.38572688357908
          ],
          [
            7.791614511076532,
            50.386475029851184
          ],
          [
            7.792044693742012,
            50.388051795786524
          ],
          [
            7.79176304277382,
            50.388540360517716
          ],
          [
            7.789341797390851,
            50.38779001414359
          ],
          [
            7.785672620179036,
            50.39328570590093
          ],
          [
            7.78647192327141,
            50.39432198715013
          ],
          [
            7.784654514943387,
            50.39554859621612
          ],
          [
            7.782896268958749,
            50.395507058795964
          ],
          [
            7.778773407493995,
            50.39640896319996
          ],
          [
            7.77746681044,
            50.39683722064276
          ],
          [
            7.776182606114598,
            50.396878834927385
          ],
          [
            7.7747124411380515,
            50.39648384912786
          ],
          [
            7.7734033130006015,
            50.39574151795229
          ],
          [
            7.772043123171849,
            50.395394123270414
          ],
          [
            7.770096332009015,
            50.39520385638142
          ],
          [
            7.76824079749221,
            50.39465557481098
          ],
          [
            7.7667849496120445,
            50.3937746223448
          ],
          [
            7.765013778592136,
            50.391778687645626
          ],
          [
            7.763522694630823,
            50.39077980334693
          ],
          [
            7.76178472468556,
            50.38991007455149
          ],
          [
            7.76050367751138,
            50.38893415844617
          ],
          [
            7.760055485378811,
            50.38816715996953
          ],
          [
            7.7597777351860735,
            50.38713410920229
          ],
          [
            7.758991534353349,
            50.38636805184556
          ],
          [
            7.7580282108377805,
            50.3857418241936
          ],
          [
            7.7528082645689,
            50.38373539641277
          ],
          [
            7.750616138918647,
            50.38365597240631
          ],
          [
            7.754229863288318,
            50.387361879601855
          ],
          [
            7.754434101008694,
            50.39037402711404
          ],
          [
            7.75735114924347,
            50.393964137649405
          ],
          [
            7.757440976144,
            50.39942257802819
          ],
          [
            7.755972719940912,
            50.400684095529996
          ],
          [
            7.746910709931938,
            50.396667863045586
          ],
          [
            7.744621810729137,
            50.39630690230552
          ],
          [
            7.74190644044042,
            50.39097453831225
          ],
          [
            7.74401204178205,
            50.38869303797453
          ],
          [
            7.740364643900901,
            50.38629154423943
          ],
          [
            7.741930685618472,
            50.383123757027136
          ],
          [
            7.735443953187802,
            50.38184243933453
          ],
          [
            7.736910269315224,
            50.3803740506316
          ],
          [
            7.736101287645855,
            50.38000344852197
          ],
          [
            7.736561522855609,
            50.3772053057082
          ],
          [
            7.736808900019054,
            50.37658998626748
          ],
          [
            7.736818317250513,
            50.37475342261462
          ],
          [
            7.737040730938115,
            50.37408347972446
          ],
          [
            7.737342526276533,
            50.37373958422707
          ],
          [
            7.739417936800738,
            50.372681982948926
          ],
          [
            7.738764755249192,
            50.37043683878687
          ],
          [
            7.7375563224439,
            50.36914374772612
          ],
          [
            7.736660753666231,
            50.368572978596184
          ],
          [
            7.732964782012127,
            50.367268512821646
          ],
          [
            7.732256573632816,
            50.366864288996204
          ],
          [
            7.732027845621262,
            50.36596739429104
          ],
          [
            7.732014208894706,
            50.36500364973814
          ],
          [
            7.728691036283515,
            50.364545380588815
          ],
          [
            7.726234093173286,
            50.36562959060982
          ],
          [
            7.727438492613573,
            50.36788262501756
          ],
          [
            7.724083278723191,
            50.36844089696339
          ],
          [
            7.7214224911613405,
            50.36558536625296
          ],
          [
            7.719804981807398,
            50.365405672504814
          ],
          [
            7.7191075975782235,
            50.36460263790947
          ],
          [
            7.7156275863326655,
            50.36384856099135
          ],
          [
            7.712584133094179,
            50.36270611448612
          ],
          [
            7.710449237049112,
            50.361204658205644
          ],
          [
            7.707360502527443,
            50.3605983850184
          ],
          [
            7.699414963040902,
            50.35811794774101
          ],
          [
            7.698965382577131,
            50.357395668077686
          ],
          [
            7.7021149360085746,
            50.35721130181248
          ],
          [
            7.702659002962759,
            50.356819370459164
          ],
          [
            7.698195093535528,
            50.35426148667859
          ],
          [
            7.698731437667874,
            50.35258180878997
          ],
          [
            7.697688924033738,
            50.35165597653542
          ],
          [
            7.695626797864806,
            50.35225394080993
          ],
          [
            7.695395000661991,
            50.35354486457846
          ],
          [
            7.6961337050308325,
            50.35437326223985
          ],
          [
            7.6954710819723005,
            50.355572633443415
          ],
          [
            7.69254031149262,
            50.35657252853768
          ],
          [
            7.69241581884171,
            50.35747889672247
          ],
          [
            7.688865407624575,
            50.3601293133592
          ],
          [
            7.689954316821532,
            50.36075022197474
          ],
          [
            7.690985324678411,
            50.36257625018583
          ],
          [
            7.695963727197078,
            50.366191433504135
          ],
          [
            7.6930674443981575,
            50.36589561430846
          ],
          [
            7.688190384570273,
            50.36741511188948
          ],
          [
            7.687964006658458,
            50.367904797152164
          ],
          [
            7.6869169959519885,
            50.36869854217607
          ],
          [
            7.68484310169358,
            50.3690079157593
          ],
          [
            7.6851433274497545,
            50.369636554230446
          ],
          [
            7.685076854608,
            50.37192196983224
          ],
          [
            7.68647230380236,
            50.373540866528224
          ],
          [
            7.666840343194091,
            50.37900131043067
          ],
          [
            7.667102035862731,
            50.37933191232839
          ],
          [
            7.66730688864898,
            50.38013833523415
          ],
          [
            7.66599257157243,
            50.381384531882
          ],
          [
            7.6652218945080195,
            50.38155461500946
          ],
          [
            7.66405429534346,
            50.38153481587487
          ],
          [
            7.663582793101435,
            50.383747223172875
          ],
          [
            7.662101330092407,
            50.38425991351843
          ],
          [
            7.661296793612581,
            50.38335763246849
          ],
          [
            7.659883586278054,
            50.38343977683425
          ],
          [
            7.659575384828278,
            50.38504391975813
          ],
          [
            7.656842970644758,
            50.38365274113603
          ],
          [
            7.654680410443203,
            50.38308598549995
          ],
          [
            7.6485276286208865,
            50.38376190440002
          ],
          [
            7.649030327993876,
            50.386385618220864
          ],
          [
            7.646196860489077,
            50.387125694196946
          ],
          [
            7.64653286699175,
            50.38785437981127
          ],
          [
            7.644520095832462,
            50.388992967986184
          ],
          [
            7.6446281775670855,
            50.39092257577822
          ],
          [
            7.644089899840752,
            50.391899679523874
          ],
          [
            7.64517594120117,
            50.39303418464274
          ],
          [
            7.647707503618556,
            50.39309702125544
          ],
          [
            7.646758547189281,
            50.39527052412326
          ],
          [
            7.647208023771456,
            50.39830712464171
          ],
          [
            7.650083733209131,
            50.399900165770006
          ],
          [
            7.6544985734199145,
            50.399577301833176
          ],
          [
            7.65831728441143,
            50.39886135974072
          ],
          [
            7.6605551658542135,
            50.39982607538058
          ],
          [
            7.662900606350939,
            50.39924467119017
          ],
          [
            7.665307015818897,
            50.39928601502081
          ],
          [
            7.6663749310190505,
            50.399564456227985
          ],
          [
            7.669592202683631,
            50.40134549266364
          ],
          [
            7.670512493880144,
            50.40150320525731
          ],
          [
            7.672689628152875,
            50.40137667421895
          ],
          [
            7.673739233949312,
            50.401024301887205
          ],
          [
            7.674302438161381,
            50.40056092224186
          ],
          [
            7.679470690241788,
            50.403407069580005
          ],
          [
            7.680986555058818,
            50.405614241369406
          ],
          [
            7.675079635923828,
            50.40825157864483
          ],
          [
            7.6721039653475325,
            50.41133891806413
          ],
          [
            7.669488421293108,
            50.41335454866748
          ],
          [
            7.670806071259357,
            50.415340880668026
          ],
          [
            7.670374699271361,
            50.41595155941738
          ],
          [
            7.66828567365702,
            50.41577408936716
          ],
          [
            7.668017646109055,
            50.416947042962484
          ],
          [
            7.668263758990164,
            50.418240705309174
          ],
          [
            7.669808893011718,
            50.419260192165375
          ],
          [
            7.6711652140671225,
            50.419905841186356
          ],
          [
            7.67038468342123,
            50.420697022511575
          ],
          [
            7.673136977395142,
            50.42133195584031
          ],
          [
            7.66850952419343,
            50.42304600341827
          ],
          [
            7.670785041260703,
            50.42387635116691
          ],
          [
            7.675493253359342,
            50.42456831271481
          ],
          [
            7.674969314446588,
            50.42578001762335
          ],
          [
            7.668172099399137,
            50.42490157150611
          ],
          [
            7.665586958322891,
            50.42406354392221
          ],
          [
            7.66424867539177,
            50.425498762885844
          ],
          [
            7.662210519871943,
            50.425901158419386
          ],
          [
            7.659851999404992,
            50.42566892720395
          ],
          [
            7.6583663779059465,
            50.42646063412341
          ],
          [
            7.657218879273168,
            50.42771989649983
          ],
          [
            7.655038120487994,
            50.42835031652549
          ],
          [
            7.6534646115330975,
            50.429193816890724
          ],
          [
            7.652696613092454,
            50.430003208502434
          ],
          [
            7.652320522900712,
            50.43085831337739
          ],
          [
            7.651622964955839,
            50.43143533054369
          ],
          [
            7.652305923026011,
            50.43202851103261
          ],
          [
            7.652649877435261,
            50.43286541880154
          ],
          [
            7.651842848741494,
            50.43361981505061
          ],
          [
            7.649610587679099,
            50.433699603036956
          ],
          [
            7.647767160092324,
            50.434572363205625
          ],
          [
            7.646149983641438,
            50.43450525242632
          ],
          [
            7.64454236942146,
            50.43474450362148
          ],
          [
            7.640980838520218,
            50.43720429871244
          ],
          [
            7.639969456595,
            50.43714314848074
          ],
          [
            7.639163113123094,
            50.438806920887956
          ],
          [
            7.6406636445265494,
            50.43940248531869
          ],
          [
            7.639617359820582,
            50.44037596783087
          ],
          [
            7.638212509949174,
            50.442141915044715
          ],
          [
            7.636732950746805,
            50.44305057314549
          ],
          [
            7.635988010282297,
            50.444859926957356
          ],
          [
            7.635057630843761,
            50.44554811747811
          ],
          [
            7.6332345384822275,
            50.44584488850944
          ],
          [
            7.631717129414308,
            50.44644639508804
          ],
          [
            7.634537679264923,
            50.447597179070065
          ],
          [
            7.63577949318825,
            50.44827640450237
          ],
          [
            7.637681856358761,
            50.44853082960789
          ],
          [
            7.638679572648702,
            50.44835754052771
          ],
          [
            7.6395363060486075,
            50.44841485291397
          ],
          [
            7.642906969604872,
            50.450263425035146
          ],
          [
            7.6431047508797265,
            50.45095266499086
          ],
          [
            7.642738720225095,
            50.45163691492524
          ],
          [
            7.642807881811509,
            50.45189075361223
          ],
          [
            7.644388042479665,
            50.45234416531242
          ],
          [
            7.648741067289064,
            50.45544150903957
          ],
          [
            7.64725829921311,
            50.4568634759856
          ],
          [
            7.64753713642972,
            50.45807696626187
          ],
          [
            7.64839860302792,
            50.45875562420594
          ],
          [
            7.6478473086034375,
            50.4594713185617
          ],
          [
            7.64682491680406,
            50.45981516309507
          ],
          [
            7.644087871134626,
            50.457739328397054
          ],
          [
            7.642984237248821,
            50.45640631282736
          ],
          [
            7.640927483317636,
            50.4556709181315
          ],
          [
            7.637795588535777,
            50.4556831346812
          ],
          [
            7.635732361307302,
            50.45505553615907
          ],
          [
            7.635245715414156,
            50.45401692582395
          ],
          [
            7.634239700932091,
            50.45293837081667
          ],
          [
            7.632253505480595,
            50.451745346112475
          ],
          [
            7.6308832273058895,
            50.449937330128336
          ],
          [
            7.630381225690196,
            50.448691211237694
          ],
          [
            7.62955518320047,
            50.4476711234296
          ],
          [
            7.627357944639236,
            50.445554291017004
          ],
          [
            7.626001013739361,
            50.443764550314555
          ],
          [
            7.626961443243068,
            50.442356826685426
          ],
          [
            7.626296984751498,
            50.44238525886048
          ],
          [
            7.625313739828351,
            50.442783910910336
          ],
          [
            7.624468578186562,
            50.4436902537838
          ],
          [
            7.623804517392245,
            50.444862246180705
          ],
          [
            7.622710009470603,
            50.44592442643419
          ],
          [
            7.622305933534123,
            50.446994857930775
          ],
          [
            7.621694197593648,
            50.44777195312171
          ],
          [
            7.618750853730934,
            50.448625769353725
          ],
          [
            7.618544065836314,
            50.44900778486659
          ],
          [
            7.619151770707823,
            50.449905434564016
          ],
          [
            7.61912582776995,
            50.45032799520665
          ],
          [
            7.618677445087017,
            50.45073998197767
          ],
          [
            7.618128274310066,
            50.45072623362394
          ],
          [
            7.6177436635812175,
            50.45032941103895
          ],
          [
            7.616985770984157,
            50.45004029604912
          ],
          [
            7.616589007865422,
            50.45030049184668
          ],
          [
            7.6165702238359545,
            50.450606173601614
          ],
          [
            7.6171917208214115,
            50.45127906770729
          ],
          [
            7.617219596492588,
            50.45197311058889
          ],
          [
            7.616841590297084,
            50.452386853557144
          ],
          [
            7.614578815253533,
            50.45271734759707
          ],
          [
            7.6129918447551965,
            50.453983208358686
          ],
          [
            7.6128832115376595,
            50.45506102368882
          ],
          [
            7.6138259875198315,
            50.45738981590231
          ],
          [
            7.615430350617188,
            50.45790726557772
          ],
          [
            7.616621621452718,
            50.45872049882674
          ],
          [
            7.616835053410695,
            50.46006751211591
          ],
          [
            7.61438051867767,
            50.460528276629624
          ],
          [
            7.614039398033031,
            50.46125809480791
          ],
          [
            7.602948177575911,
            50.46337474496735
          ],
          [
            7.598346273833137,
            50.46456452098045
          ],
          [
            7.595671544462304,
            50.467207462641035
          ],
          [
            7.594935157665102,
            50.469530079789564
          ],
          [
            7.596452618549445,
            50.47327824267858
          ],
          [
            7.594950047610804,
            50.47521235375828
          ],
          [
            7.596773343878093,
            50.47630286494322
          ],
          [
            7.597824818496674,
            50.47618529362019
          ],
          [
            7.599663985806186,
            50.47793349019987
          ],
          [
            7.5992626283291305,
            50.47849067025164
          ],
          [
            7.60036329619566,
            50.479175720349524
          ],
          [
            7.602818240294614,
            50.47918347344515
          ],
          [
            7.603648631293122,
            50.47944748193777
          ],
          [
            7.6040936076937795,
            50.47978283507669
          ],
          [
            7.60422604451124,
            50.48038046533374
          ],
          [
            7.603503279457038,
            50.48134378766852
          ],
          [
            7.602878507780214,
            50.48163422922212
          ],
          [
            7.602722604856361,
            50.481873430752145
          ],
          [
            7.602926741882033,
            50.48199562478456
          ],
          [
            7.608713729960644,
            50.481294611088515
          ],
          [
            7.609995957387765,
            50.48132679130072
          ],
          [
            7.610889124242355,
            50.48171838406692
          ],
          [
            7.611258735921063,
            50.48213285796565
          ],
          [
            7.611525287993278,
            50.482616782217654
          ],
          [
            7.611323455486908,
            50.483602217578444
          ],
          [
            7.611495009429498,
            50.483795614684624
          ],
          [
            7.613585188217344,
            50.484001088114105
          ],
          [
            7.614470430598528,
            50.484293403022455
          ],
          [
            7.615323892921455,
            50.484873058964595
          ],
          [
            7.615957152712349,
            50.48559126690335
          ],
          [
            7.616370505475655,
            50.4857546918741
          ],
          [
            7.617666951870576,
            50.48578713950903
          ],
          [
            7.620140223217486,
            50.48619117042523
          ],
          [
            7.620640067260364,
            50.48609561213679
          ],
          [
            7.6223105570688245,
            50.48509283828295
          ],
          [
            7.62348758332342,
            50.484771063364036
          ],
          [
            7.627328527242364,
            50.48496596580569
          ],
          [
            7.630463908025231,
            50.4844678328579
          ],
          [
            7.631474097729507,
            50.48456502962365
          ],
          [
            7.632817339785715,
            50.48498566261277
          ],
          [
            7.633829899026238,
            50.4855061046338
          ],
          [
            7.63422188259147,
            50.48602010429789
          ],
          [
            7.634649171865834,
            50.48711126273782
          ],
          [
            7.635104880314957,
            50.487275672120134
          ],
          [
            7.635551270872223,
            50.486899583709615
          ],
          [
            7.635904138605011,
            50.48620601442066
          ],
          [
            7.636935053103997,
            50.48550228612015
          ],
          [
            7.638134312328978,
            50.48504585060074
          ],
          [
            7.640367939463956,
            50.48498426646423
          ],
          [
            7.640753736541895,
            50.4851379135246
          ],
          [
            7.640793656547027,
            50.48540903575648
          ],
          [
            7.639871318254288,
            50.48595341412462
          ],
          [
            7.63940906429386,
            50.48659025139202
          ],
          [
            7.639504249968512,
            50.48688075541557
          ],
          [
            7.640826410522535,
            50.48741782508208
          ],
          [
            7.641919596172664,
            50.48754400126369
          ],
          [
            7.643374016062493,
            50.48730094203329
          ],
          [
            7.644907784374395,
            50.48668164843899
          ],
          [
            7.6469541675212644,
            50.48621910253547
          ],
          [
            7.6486543466332995,
            50.485414791556046
          ],
          [
            7.649975280975071,
            50.48527639923651
          ],
          [
            7.650674413083939,
            50.485383738344886
          ],
          [
            7.651655717777113,
            50.48595727148576
          ],
          [
            7.651796970124887,
            50.48641998477073
          ],
          [
            7.651621638218574,
            50.486982922049876
          ],
          [
            7.650789847494043,
            50.48766468934259
          ],
          [
            7.650734890420464,
            50.48810454228369
          ],
          [
            7.651052245818428,
            50.48868866841716
          ],
          [
            7.651554349602268,
            50.48948446131072
          ],
          [
            7.651894117484728,
            50.48969996144249
          ],
          [
            7.652608062710361,
            50.48956453659589
          ],
          [
            7.653346815078936,
            50.48971785865997
          ],
          [
            7.6542011155263605,
            50.490990565474085
          ],
          [
            7.653945501997537,
            50.49171360066979
          ],
          [
            7.653956541913493,
            50.49385690106201
          ],
          [
            7.654205686006222,
            50.49440331440195
          ],
          [
            7.654491305612869,
            50.49458145097971
          ],
          [
            7.655026905718828,
            50.494594677910406
          ],
          [
            7.655822844763321,
            50.49427216567411
          ],
          [
            7.656550019836228,
            50.4936868262475
          ],
          [
            7.657623538442855,
            50.4932090753111
          ],
          [
            7.660294518538499,
            50.492923773782664
          ],
          [
            7.661491929630928,
            50.49319639733196
          ],
          [
            7.662250194160201,
            50.493728320670826
          ],
          [
            7.662804620556346,
            50.494363270428906
          ],
          [
            7.663145904092885,
            50.49548820439945
          ],
          [
            7.664143935327795,
            50.49555779513976
          ],
          [
            7.664706781270081,
            50.49488732300827
          ],
          [
            7.665475752642125,
            50.493375519160445
          ],
          [
            7.6662423235104145,
            50.49307022323626
          ],
          [
            7.666271634434382,
            50.49281882490925
          ],
          [
            7.665768663946236,
            50.492266196811386
          ],
          [
            7.665970366463005,
            50.491965013869304
          ],
          [
            7.667253619647778,
            50.490817016750256
          ],
          [
            7.668029912604317,
            50.49034987282727
          ],
          [
            7.669366650705198,
            50.490184631980924
          ],
          [
            7.669964531846186,
            50.490334384537626
          ],
          [
            7.671757639987958,
            50.49126083425831
          ],
          [
            7.672900868053858,
            50.49149599158932
          ],
          [
            7.673341032880732,
            50.4919209865772
          ],
          [
            7.674341752691802,
            50.49381841346016
          ],
          [
            7.674681656649321,
            50.494033846441816
          ],
          [
            7.675203161446892,
            50.49404663398145
          ],
          [
            7.6758905918381855,
            50.494819840524954
          ],
          [
            7.678542769244941,
            50.496253458434175
          ],
          [
            7.6790564409660735,
            50.49850808212384
          ],
          [
            7.678330087976427,
            50.499786902475336
          ],
          [
            7.675074960367716,
            50.50156201416404
          ],
          [
            7.674494845013962,
            50.502754356949374
          ],
          [
            7.673153967229533,
            50.50391903373416
          ],
          [
            7.6701397505930835,
            50.50426825245506
          ],
          [
            7.668326447531495,
            50.50530421960644
          ],
          [
            7.671457708905056,
            50.50886575924723
          ],
          [
            7.672257504129918,
            50.511523627230005
          ],
          [
            7.673577486921108,
            50.513284817381006
          ],
          [
            7.669528194219801,
            50.51673312313165
          ],
          [
            7.668289208673435,
            50.51877367164094
          ],
          [
            7.671402940703488,
            50.52193857491677
          ],
          [
            7.67802576166269,
            50.52524335641165
          ],
          [
            7.686869564812255,
            50.527098249126574
          ],
          [
            7.692251006975087,
            50.525689719373766
          ],
          [
            7.6955193790188385,
            50.52795727388653
          ],
          [
            7.69650939039297,
            50.53006130435406
          ],
          [
            7.696532187491706,
            50.53227687424831
          ],
          [
            7.697807409915075,
            50.53481101797376
          ],
          [
            7.69965648888765,
            50.537674225026294
          ],
          [
            7.699062933929514,
            50.54074822271827
          ],
          [
            7.699564875645113,
            50.54217205052544
          ],
          [
            7.703010122066551,
            50.54257723661141
          ],
          [
            7.701046379798043,
            50.54822476798411
          ],
          [
            7.701467195120144,
            50.54945953741004
          ],
          [
            7.691948406104156,
            50.55053380729548
          ],
          [
            7.69360117871616,
            50.55196066805619
          ],
          [
            7.693033406420079,
            50.55318042214951
          ],
          [
            7.6997486477751025,
            50.55877916333115
          ],
          [
            7.704229132931257,
            50.56166403594321
          ],
          [
            7.699706981421188,
            50.566641681110276
          ],
          [
            7.695431278780829,
            50.56788483606754
          ],
          [
            7.694897462881211,
            50.568775917339394
          ],
          [
            7.697866692327138,
            50.57136921229575
          ],
          [
            7.698176588106595,
            50.572097066776195
          ],
          [
            7.698241841735285,
            50.57431366645987
          ],
          [
            7.698381542853609,
            50.57457817751905
          ],
          [
            7.693238713539676,
            50.57521857274327
          ],
          [
            7.692176830271527,
            50.571942243074695
          ],
          [
            7.689908810776682,
            50.57227421830661
          ],
          [
            7.687308102401586,
            50.56967168379162
          ],
          [
            7.684661603913398,
            50.56736510485882
          ],
          [
            7.683944019757857,
            50.56824801451109
          ],
          [
            7.683834049762102,
            50.56937085513819
          ],
          [
            7.684149718238401,
            50.57023395665502
          ],
          [
            7.68496818029559,
            50.57096525587188
          ],
          [
            7.685969312491797,
            50.57242133790739
          ],
          [
            7.686534378384708,
            50.57360565877075
          ],
          [
            7.686013285241305,
            50.57639325582133
          ],
          [
            7.686341063804933,
            50.577526770070435
          ],
          [
            7.687392305621409,
            50.578857998442984
          ],
          [
            7.6877806531055235,
            50.579794054013476
          ],
          [
            7.685811530592883,
            50.58329578141598
          ],
          [
            7.685884556582023,
            50.5844128473322
          ],
          [
            7.685578923105716,
            50.58502668507177
          ],
          [
            7.68512226266315,
            50.585564806080185
          ],
          [
            7.683827545710454,
            50.58639763079013
          ],
          [
            7.683515326698977,
            50.58688524462571
          ],
          [
            7.683617200261034,
            50.588247363923266
          ],
          [
            7.683398958397718,
            50.58881830820662
          ],
          [
            7.682118829782218,
            50.58987657776941
          ],
          [
            7.681890813627727,
            50.59060935698255
          ],
          [
            7.681912106569105,
            50.59119515013075
          ],
          [
            7.680798120584398,
            50.59231148796878
          ],
          [
            7.68020290152543,
            50.59350351685546
          ],
          [
            7.674939842606749,
            50.59375303541096
          ],
          [
            7.665227852723469,
            50.594586498852415
          ],
          [
            7.665212394143992,
            50.59600879634008
          ],
          [
            7.665654100141292,
            50.59922516483211
          ],
          [
            7.666248863029046,
            50.600383305980316
          ],
          [
            7.668794209458169,
            50.602273607873464
          ],
          [
            7.674267108023076,
            50.61215024891998
          ],
          [
            7.675921556808506,
            50.614279695074046
          ],
          [
            7.679819952330015,
            50.61346551578344
          ],
          [
            7.679931333387154,
            50.614051362645164
          ],
          [
            7.681096244944733,
            50.61485168532118
          ],
          [
            7.684670081609777,
            50.61587990306978
          ],
          [
            7.687345877164373,
            50.61609815899253
          ],
          [
            7.688421035307303,
            50.61634043348368
          ],
          [
            7.689474047205384,
            50.616951329908545
          ],
          [
            7.689815035836164,
            50.61743695753483
          ],
          [
            7.6907618540582074,
            50.61813181212342
          ],
          [
            7.691193547092803,
            50.61879983941448
          ],
          [
            7.691735569582989,
            50.619127488359
          ],
          [
            7.693685290529269,
            50.6194128017436
          ],
          [
            7.696856559649073,
            50.620281038540355
          ],
          [
            7.697540484800645,
            50.621241041636495
          ],
          [
            7.699230889706321,
            50.622654266949766
          ],
          [
            7.700820994767107,
            50.62291744929847
          ],
          [
            7.703223585550995,
            50.62274152966455
          ],
          [
            7.702279606448999,
            50.62929167527339
          ],
          [
            7.701922794720626,
            50.635252762251476
          ],
          [
            7.701029399034136,
            50.640714634281885
          ],
          [
            7.704221553089648,
            50.643214000785115
          ],
          [
            7.702771364551676,
            50.64615026891366
          ],
          [
            7.704168384566267,
            50.64670630624457
          ],
          [
            7.703360260638997,
            50.64766820432864
          ],
          [
            7.704027895625936,
            50.65473456718583
          ],
          [
            7.700554702405116,
            50.656676443357
          ],
          [
            7.701135041740509,
            50.65808484071752
          ],
          [
            7.699614326015085,
            50.658161944580655
          ],
          [
            7.6978923172169615,
            50.6585051745266
          ],
          [
            7.69413256183255,
            50.659600178989784
          ],
          [
            7.692695044495498,
            50.66042067925531
          ],
          [
            7.691018707690952,
            50.662637428096154
          ],
          [
            7.694736559657219,
            50.66463914765828
          ],
          [
            7.694679861956784,
            50.6655832073037
          ],
          [
            7.693373952638638,
            50.66538944387453
          ],
          [
            7.691532748046825,
            50.66679441016904
          ],
          [
            7.692868059055281,
            50.66956409489133
          ],
          [
            7.696105728974119,
            50.67298317406595
          ],
          [
            7.697761858781879,
            50.67230298274496
          ],
          [
            7.702224703786376,
            50.67420284779763
          ],
          [
            7.702500979902853,
            50.674794797558995
          ],
          [
            7.705605095304402,
            50.67477979569182
          ],
          [
            7.706265230499274,
            50.67389389535413
          ],
          [
            7.710121625996102,
            50.67365527188042
          ],
          [
            7.710851986293302,
            50.67305160675079
          ],
          [
            7.712577574549613,
            50.67239089169791
          ],
          [
            7.714512868273243,
            50.672014328632564
          ],
          [
            7.720727852649011,
            50.672578034053004
          ],
          [
            7.726276075209142,
            50.677690439220264
          ],
          [
            7.72611107418826,
            50.681574736457215
          ],
          [
            7.725688087974277,
            50.682455359882574
          ],
          [
            7.726356257456712,
            50.68361756855335
          ],
          [
            7.72561316283267,
            50.68884850162152
          ],
          [
            7.724570288070298,
            50.68946277260121
          ],
          [
            7.716550216473031,
            50.69310772262585
          ],
          [
            7.710171702307497,
            50.69369053367936
          ],
          [
            7.705168617242999,
            50.69391194953252
          ],
          [
            7.7034279089689,
            50.69362677976701
          ],
          [
            7.700270907769106,
            50.69379354379395
          ],
          [
            7.699895441741791,
            50.69603548677254
          ],
          [
            7.698695180007237,
            50.698432384792305
          ],
          [
            7.695758060977375,
            50.70260735474676
          ],
          [
            7.695889199773781,
            50.7046724785065
          ],
          [
            7.696819199942376,
            50.706657907584415
          ],
          [
            7.6988675104006665,
            50.707968076133376
          ],
          [
            7.7018166354241275,
            50.70915592117349
          ],
          [
            7.70807381362064,
            50.71241342801039
          ],
          [
            7.7078456063881,
            50.713146257512584
          ],
          [
            7.710496447853007,
            50.71387646965869
          ],
          [
            7.715166019155255,
            50.7159517836404
          ],
          [
            7.718665588104281,
            50.714820375495016
          ],
          [
            7.724580878229298,
            50.71598880607693
          ],
          [
            7.727707263009011,
            50.71731527288567
          ],
          [
            7.728871654270942,
            50.71991828807519
          ],
          [
            7.731626914496445,
            50.720812569909874
          ],
          [
            7.731062152357307,
            50.7226808924535
          ],
          [
            7.731374880082296,
            50.72314757321366
          ],
          [
            7.735224117414404,
            50.72473420989005
          ],
          [
            7.735450845008828,
            50.72521683259276
          ],
          [
            7.735299159687065,
            50.72586149468173
          ],
          [
            7.733291110876346,
            50.72719113471007
          ],
          [
            7.732338817860128,
            50.727222400261375
          ],
          [
            7.731831765462963,
            50.72692215270322
          ],
          [
            7.731479179914432,
            50.726409501141795
          ],
          [
            7.7293227401170554,
            50.724503102038156
          ],
          [
            7.726073149532205,
            50.724047126647086
          ],
          [
            7.72234120822664,
            50.72383159974233
          ],
          [
            7.721570592118533,
            50.72248051658473
          ],
          [
            7.719601719454897,
            50.72291046381985
          ],
          [
            7.717629723278547,
            50.724105645544135
          ],
          [
            7.716266288250277,
            50.726035751390654
          ],
          [
            7.720162341416855,
            50.73111757712897
          ],
          [
            7.7227949935962,
            50.73050544571014
          ],
          [
            7.723538923816709,
            50.729685913512824
          ],
          [
            7.724633748098027,
            50.72940602344519
          ],
          [
            7.725102317232344,
            50.728922033701366
          ],
          [
            7.725892429432753,
            50.727563355489735
          ],
          [
            7.726371390327685,
            50.72714263819395
          ],
          [
            7.726899255398925,
            50.72709225360994
          ],
          [
            7.727575458502233,
            50.727171474195536
          ],
          [
            7.728662485653361,
            50.72773773481526
          ],
          [
            7.728966677538479,
            50.728348281014696
          ],
          [
            7.72896804876255,
            50.72904161962831
          ],
          [
            7.728900980486389,
            50.72945419731641
          ],
          [
            7.725579598772646,
            50.73282319245635
          ],
          [
            7.725493514247054,
            50.73331634925326
          ],
          [
            7.725789416124156,
            50.73382766135901
          ],
          [
            7.726857863783893,
            50.73423141888125
          ],
          [
            7.728201120278545,
            50.73430859679286
          ],
          [
            7.729023101335878,
            50.73408516041884
          ],
          [
            7.731120505953394,
            50.731974376665804
          ],
          [
            7.734721347486376,
            50.73058377160405
          ],
          [
            7.736966491505335,
            50.73004310435573
          ],
          [
            7.738222722700351,
            50.72991100168273
          ],
          [
            7.73938011330548,
            50.73001063121746
          ],
          [
            7.740187937424705,
            50.730263988903744
          ],
          [
            7.740712581829298,
            50.73098780097814
          ],
          [
            7.740661664253801,
            50.73232817127846
          ],
          [
            7.742013207910748,
            50.73250443030089
          ],
          [
            7.743463768074045,
            50.73148551110477
          ],
          [
            7.743903475795404,
            50.730046348867596
          ],
          [
            7.745491187826899,
            50.730066119276714
          ],
          [
            7.746239761102786,
            50.73108335529137
          ],
          [
            7.7499818294083545,
            50.73306309552943
          ],
          [
            7.746967211827651,
            50.73630489868464
          ],
          [
            7.743938183238502,
            50.73714224890922
          ],
          [
            7.7423670578734995,
            50.73707783834226
          ],
          [
            7.7415503689692935,
            50.73793176888532
          ],
          [
            7.742293505631031,
            50.73856173167917
          ],
          [
            7.742885385355521,
            50.74007047120716
          ],
          [
            7.746978961054357,
            50.739951751643304
          ]
        ],
        [
          [
            7.700788416523473,
            50.599821095778275
          ],
          [
            7.699278655785141,
            50.59715528294367
          ],
          [
            7.6946774745319235,
            50.59957375167268
          ],
          [
            7.6917789867524595,
            50.598602882520694
          ],
          [
            7.689717884856173,
            50.59617563743582
          ],
          [
            7.694857029046836,
            50.5930411038529
          ],
          [
            7.699716238345898,
            50.5898455440411
          ],
          [
            7.700777376041984,
            50.58747618243777
          ],
          [
            7.700493280464507,
            50.583714575946956
          ],
          [
            7.694425202529667,
            50.582315676203244
          ],
          [
            7.695548958500871,
            50.580082944597734
          ],
          [
            7.698508818194311,
            50.580010755724714
          ],
          [
            7.701826370514537,
            50.58317963935397
          ],
          [
            7.703259001862653,
            50.585474389080204
          ],
          [
            7.705900020259834,
            50.58648377304193
          ],
          [
            7.706114128301755,
            50.58739836841445
          ],
          [
            7.705133450372089,
            50.58866221633958
          ],
          [
            7.706965541382775,
            50.58924680069575
          ],
          [
            7.708099331733057,
            50.59086794780665
          ],
          [
            7.709149344659635,
            50.59081229816856
          ],
          [
            7.70939250140384,
            50.59195268961353
          ],
          [
            7.710139873733427,
            50.593177297621054
          ],
          [
            7.711472695837263,
            50.59478520754496
          ],
          [
            7.71139325327915,
            50.59730442812204
          ],
          [
            7.704762726486062,
            50.599602225664434
          ],
          [
            7.703775396386178,
            50.59860587803119
          ],
          [
            7.700788416523473,
            50.599821095778275
          ]
        ]
      ]
    ]
  }
}